tests/__init__.py
tests/test_todo.py
Todos/__init__.py
Todos/colorizer.py
Todos/consts.py
Todos/exc.py
Todos/log.py
Todos/todo.py
Todos/utils.py
todos-0.2.1.dist-info/DESCRIPTION.rst
todos-0.2.1.dist-info/entry_points.txt
todos-0.2.1.dist-info/METADATA
todos-0.2.1.dist-info/metadata.json
todos-0.2.1.dist-info/RECORD
todos-0.2.1.dist-info/top_level.txt
todos-0.2.1.dist-info/WHEEL
