Metadata-Version: 2.0
Name: todos
Version: 0.2.1
Summary: Command line lightweight todo tool with readable storage ,            written in Py
Home-page: https://github.com/MrKiven/Todo.py
Author: kiven
Author-email: kiven.mr@gmail.com
License: UNKNOWN
Platform: UNKNOWN
Requires-Dist: click (==5.1)
Requires-Dist: emoji (==0.3.9)
